stratigraph/__init__.py
stratigraph/stratigraph.py
stratigraph-0.1.2.dist-info/LICENSE.txt
stratigraph-0.1.2.dist-info/METADATA
stratigraph-0.1.2.dist-info/WHEEL
stratigraph-0.1.2.dist-info/top_level.txt
stratigraph-0.1.2.dist-info/RECORD
