Metadata-Version: 2.1
Name: stratigraph
Version: 0.1.2
Summary: A Python module for stratigraphic visualization and analysis
Home-page: https://github.com/zsylvester/stratigraph
Author: Zoltan Sylvester
Author-email: zoltan.sylvester@beg.utexas.edu
Keywords: geology,geoscience,stratigraphy,chronostratigraphy,visualization
Classifier: Programming Language :: Python :: 3
Classifier: Intended Audience :: Science/Research
Classifier: License :: OSI Approved :: MIT License
Classifier: Operating System :: OS Independent
License-File: LICENSE.txt
Requires-Dist: numpy
Requires-Dist: scipy
Requires-Dist: scikit-learn
Requires-Dist: scikit-image
Requires-Dist: shapely
Requires-Dist: pillow
Requires-Dist: matplotlib
Requires-Dist: mayavi
Requires-Dist: tqdm
